<?xml version="1.0" encoding="UTF-8" standalone="yes"?>
<addon id="repository.kodi.mirror.nju"
		name="Kodi Add-on Repository Chinese NJU Mirrors"
		version="0.1.0"
		provider-name="Snowdream Tech">
	<extension point="xbmc.addon.repository" name="Kodi Add-on Repository Chinese NJU Mirrors">
		<info>https://mirrors.nju.edu.cn/kodi/addons/matrix/addons.xml.gz</info>
		<checksum>https://mirrors.nju.edu.cn/kodi/addons/matrix/addons.xml.gz</checksum>
		<datadir>https://mirrors.nju.edu.cn/kodi/addons/matrix</datadir>
		<hashes>false</hashes>
	</extension>
	<extension point="xbmc.addon.metadata">
        <summary>Kodi Add-on Repository Chinese NJU Mirrors</summary>
        <summary lang="zh">官方插件库在南京大学开源站的镜像库</summary>
        <description>Kodi Add-on Repository Chinese NJU Mirrors</description>
        <description lang="zh">本插件是一个库，提供官方插件库在南京大学开源站的镜像下载，该镜像站点每日同步官方库中全部插件内容。[CR][CR]通过本插件库，在中国无法连接官方插件库时，可以实现官方库中所有插件的安装及更新，可以完整取代官方插件库（即Kodi Add-on Repository）。</description>
        <disclaimer>Snowdream Tech is not responsible for any content in this library, which comes from NJU Synchronized Official Plug-in Library.</disclaimer>
        <disclaimer lang="zh">本库中由南京大学镜像站同步官方插件库而来，Snowdream Tech对任何内容不承担责任。</disclaimer>
		<platform>all</platform>
	</extension>
</addon>
